[{"couch":"WESTERN","ajio":"WESTERN","koovs":"WESTERN","jabong":"WESTERN","myntra":"WESTERN","stalkBuyLove":"WESTERN","luluAndSky":"WESTERN","yepme":"WESTERN","bewakoof":"WESTERN","faballey":"WESTERN","chumbak":"WESTERN","shopNineteen":"WESTERN","forever21":"WESTERN","mango":"WESTERN"},{"couch":"Tops","ajio":"tops","koovs":"top","jabong":"Women Tops","myntra":"Tops","stalkBuyLove":"Women Tees Tops, Women Crop Tops, Women Blouse, Women Off Shoulder Tops, Women Spaghetti &amp; Tanks Tops","luluAndSky":"Tops","yepme":"Tops for Women","bewakoof":"Crop tops for women, Plain topwear for women","faballey":"Tops","chumbak":"Tops &amp; blouses","shopNineteen":"Tops","forever21":"top_blouses, top_crop-tops","mango":"short_sleeve_top, long_sleeve_top, tops"},{"couch":"Shirts","ajio":"shirt","koovs":"Shirts","jabong":"Women Shirts","myntra":"Shirts","stalkBuyLove":"Women Shirts","bewakoof":"Shirts","chumbak":"Shirts &amp; buttondowns","mango":"blouses_shirt, sleveless_shirt, short_sleeve_shirt, long_sleeve_shirt, denim_shirt"},{"couch":"T-Shirts & Vests","ajio":"tshirt","koovs":"T Shirts","jabong":"Women Tees","myntra":"T-Shirts & Vests","stalkBuyLove":"-","luluAndSky":"T Shirts, Tanks and Cami","yepme":"T Shirts","bewakoof":"T shirts for women, Full sleeve t shirts, Tank tops for women","chumbak":"T-shirts, Tank tops &amp; camisoles","forever21":"top_t-shirts, top_basic, top_graphic-tees, top_camis_tanks","mango":"tank_top"},{"couch":"Dresses","ajio":"dresses","koovs":"dress","jabong":"Women Dresses","myntra":"Dresses","stalkBuyLove":"Women Tube &amp; Spaghetti Dresses, Women Shift Dresses, Women Mini Dresses, Women Pencil Dresses, Women Midi Dresses, Women Off Shoulder Dresses,Women Skater Dresses, Women Bodycon Dresses, Women Maxi Dresses","luluAndSky":"Maxi, Gown, Cocktail, Bodycon, Casual, Denim, Dresses","yepme":"Dresses","bewakoof":"Dresses","faballey":"Dresses","chumbak":"Fit &amp; flare, Shift, A-line, Bodycon","shopNineteen":"Dresses, Cocktail Dresses","forever21":"dress","mango":"short_dresses, midi_dresses, long_dresses, day_dresses, evening_dresses"},{"couch":"Skirts","koovs":"skirt","jabong":"Flared Skirts, A-line Skirts, Pencil Skirts, Skirts for Women","myntra":"Skirts","stalkBuyLove":"Women Skirts","luluAndSky":"Skirts","yepme":"Skirts","faballey":"Skirts","chumbak":"Skirts","shopNineteen":"Skirts","forever21":"bottom_skirt","mango":"short_skirts, midi_skirts, long_skirts"},{"couch":"Shorts","koovs":"shorts","jabong":"Shorts for Women","myntra":"Shorts","stalkBuyLove":"Women Shorts","luluAndSky":"Shorts","yepme":"Shorts & Capris","faballey":"Shorts","chumbak":"Shorts","shopNineteen":"Shorts","forever21":"bottom_shorts","mango":"shorts"},{"couch":"Jeans","ajio":"jeans","koovs":"jeans","jabong":"Women Jeans","myntra":"Jeans","stalkBuyLove":"Women Jeans","luluAndSky":"Jeans","yepme":"Jeans","bewakoof":"Denim jeans","forever21":"bottom_jeans","mango":"jeans"},{"couch":"Trousers & Leggings","ajio":"leggings, trousers","koovs":"trouser","jabong":"Women Trousers","myntra":"Trousers & Leggings\n","stalkBuyLove":"Women Pants, Women Joggers","luluAndSky":"Trousers, Joggers","yepme":"Leggings, Pants, Womens Palazzo Pants","bewakoof":"Joggers","faballey":"Pants, Tights &amp; Leggings","chumbak":"Pants, Leggings","shopNineteen":"Trousers, Leggings","forever21":"bottom_leggings, bottom_pants","mango":"trousers"},{"couch":"Coats & Jackets","ajio":"jacket","koovs":"jacket","jabong":"Winter Jackets","myntra":"Coats & Jackets\n","stalkBuyLove":"Women Blazers, Women Coats Jackets, Women Biker &amp; Bomber Jackets","luluAndSky":"\nBomber Jackets, Parka, Blazer, Coat, Gilet, Faux fur, Jackets","yepme":"Jackets, Blazers","bewakoof":"Bomber jackets","faballey":"Blazers &amp; Jackets","chumbak":"Jackets","shopNineteen":"Outerwear","forever21":"outerwear_coats-and-jackets","mango":"jackets, coats"},{"couch":"Sweaters & Cardigans","ajio":"sweaters, sweatshirt","koovs":"cardigan","jabong":"Sweaters, Sweatshirts","myntra":"Sweaters & Cardigans","stalkBuyLove":"-","luluAndSky":"Sweaters, Hoodies and Jumpers","yepme":"Sweatshirts, Sweaters","bewakoof":"Sweatshirts & hoodies","faballey":"Sweaters &amp; Cardigans","chumbak":"Sweatshirts &amp; hoodies, Sweaters","forever21":"sweater","mango":"cardigans, sweaters, sweatshirts"},{"couch":"Jumpsuits & Playsuits","ajio":"jump suit","koovs":"jumpsuit","jabong":"Women Dungarees &amp; Jumpsuits","myntra":"Jumpsuits & Playsuits","stalkBuyLove":"Women Jumpsuits Overalls, Women Playsuits Overalls","luluAndSky":"Jumpsuits and Playsuits","yepme":"Jumpsuits","shopNineteen":"Rompers & Jumpsuits","forever21":"jumpsuit_romper","mango":"jumpsuits"},{"couch":"Lingerie & Swimwear","koovs":"lingerie, beachwear","jabong":"Women Bras, Women Panties, Women Beachwear, Women Shapewear, Women Lingerie Sets","myntra":"Lingerie & Swimwear","stalkBuyLove":"Women Beachwear","luluAndSky":"Resort wear","forever21":"intimates-bras, intimates-panties","mango":"bras, panties, beachwear"},{"couch":"Nightwear","jabong":"Women Sleepwear, Women Nightwear","myntra":"Nightwear\n","stalkBuyLove":"Women Nightwear","luluAndSky":"Sleepwear","bewakoof":"Pyjamas","faballey":"Pajamas &amp; Shorts","shopNineteen":"Night Wear","forever21":"intimates-loungewear","mango":"sleepwear"},{"couch":"Overalls","myntra":"Overalls","stalkBuyLove":"-","luluAndSky":"-"},{"couch":"ETHNIC","ajio":"ETHNIC","koovs":"ETHNIC","jabong":"ETHNIC","myntra":"ETHNIC","stalkBuyLove":"ETHNIC","luluAndSky":"ETHNIC","yepme":"ETHNIC","bewakoof":"ETHNIC"}]